nexus/__init__.py
nexus/__main__.py
nexus/checker.py
nexus/cli_util.py
nexus/exceptions.py
nexus/reader.py
nexus/util.py
nexus/writer.py
nexus/commands/__init__.py
nexus/commands/binary2multistate.py
nexus/commands/check.py
nexus/commands/combine.py
nexus/commands/convert.py
nexus/commands/deinterleave.py
nexus/commands/describecharacter.py
nexus/commands/describetaxa.py
nexus/commands/edit.py
nexus/commands/multistate2binary.py
nexus/commands/randomise.py
nexus/commands/tally.py
nexus/commands/trees.py
nexus/handlers/__init__.py
nexus/handlers/data.py
nexus/handlers/taxa.py
nexus/handlers/tree.py
nexus/tools/__init__.py
nexus/tools/binarise.py
nexus/tools/check_zeros.py
nexus/tools/combine_nexuses.py
nexus/tools/multistatise.py
nexus/tools/shufflenexus.py
nexus/tools/sites.py
nexus/tools/trees.py
nexus/tools/util.py
python_nexus-2.9.0.dist-info/LICENSE
python_nexus-2.9.0.dist-info/METADATA
python_nexus-2.9.0.dist-info/WHEEL
python_nexus-2.9.0.dist-info/entry_points.txt
python_nexus-2.9.0.dist-info/top_level.txt
python_nexus-2.9.0.dist-info/RECORD
