Metadata-Version: 2.1
Name: python-nexus
Version: 2.9.0
Summary: A nexus (phylogenetics) file reader (.nex, .trees)
Home-page: https://github.com/dlce-eva/python-nexus
Author: Simon Greenhill and Robert Forkel
Author-email: simon@simon.net.nz
License: BSD-2-Clause
Project-URL: Bug Tracker, https://github.com/cldf/pycldf/issues
Keywords: phylogenetics nexus newick paup splitstree
Platform: any
Classifier: Development Status :: 5 - Production/Stable
Classifier: Intended Audience :: Developers
Classifier: Intended Audience :: Science/Research
Classifier: Natural Language :: English
Classifier: Operating System :: OS Independent
Classifier: Topic :: Scientific/Engineering
Classifier: Topic :: Scientific/Engineering :: Bio-Informatics
Classifier: Topic :: Software Development :: Libraries :: Python Modules
Classifier: Programming Language :: Python :: 3
Classifier: Programming Language :: Python :: 3.7
Classifier: Programming Language :: Python :: 3.8
Classifier: Programming Language :: Python :: 3.9
Classifier: Programming Language :: Python :: 3.10
Classifier: Programming Language :: Python :: Implementation :: CPython
Classifier: Programming Language :: Python :: Implementation :: PyPy
Classifier: License :: OSI Approved :: BSD License
Requires-Python: >=3.7
Requires-Dist: clldutils (>=3.10.0)
Requires-Dist: newick (>=1.3.1)
Requires-Dist: termcolor
Provides-Extra: dev
Requires-Dist: build ; extra == 'dev'
Requires-Dist: flake8 ; extra == 'dev'
Requires-Dist: tox ; extra == 'dev'
Requires-Dist: twine ; extra == 'dev'
Requires-Dist: wheel (>=0.36) ; extra == 'dev'
Provides-Extra: test
Requires-Dist: coverage (>=4.2) ; extra == 'test'
Requires-Dist: pytest-cov ; extra == 'test'
Requires-Dist: pytest-mock ; extra == 'test'
Requires-Dist: pytest (>=5) ; extra == 'test'
